randomscm/__init__.py
randomscm/randomscm.py
randomscm/tests/test_feature_importances.py
randomscm/tests/test_max_features_param.py
randomscm/tests/test_p_param.py
randomscm-0.1.2.dist-info/LICENSE
randomscm-0.1.2.dist-info/METADATA
randomscm-0.1.2.dist-info/WHEEL
randomscm-0.1.2.dist-info/top_level.txt
randomscm-0.1.2.dist-info/RECORD
