Metadata-Version: 2.1
Name: randomscm
Version: 0.1.2
Summary: The Bootstrap aggregating version of the great SCM
Author-email: Thibaud Godon <thibaud.godon@protonmail.com>, Elina Francovic-Fontaine <elina.francovic-fontaine.1@ulaval.ca>, Baptiste Bauvin <baptiste.bauvin@lis-lab.fr>
License: Apache License
Project-URL: Homepage, https://github.com/thibgo/randomscm
Keywords: machine-learning,classification,ensemble-learning,set-covering-machine,rule-based-models
Classifier: License :: OSI Approved :: MIT License
Classifier: Programming Language :: Python
Classifier: Programming Language :: Python :: 3
Requires-Python: >=3.7
License-File: LICENSE
Requires-Dist: scikit-learn>=0.19
Requires-Dist: numpy
Requires-Dist: scipy
Requires-Dist: pyscm-ml
Provides-Extra: dev
Requires-Dist: black; extra == "dev"
